Workbook

Sheet SOTP
A1: BlackRock, Inc. — Sum-of-the-Parts Valuation
A2: Platform Compounder lens · base case · market data mid-June 2026
A4: KEY INPUTS
A5: Risk-free rate (Rf), 10Y UST | B5: 0.0445
A6: Blended equity risk premium | B6: 0.054
A7: Shares outstanding (mm) | B7: 155
A9: SUM-OF-THE-PARTS (each segment via Gordon Growth: V = FCFE × (1+g) / (Ke − g))
A10: Segment | B10: FCFE ($B) | C10: g | D10: Ke | E10: Value ($B) | F10: $ / share
A11: iShares & Public Markets | B11: 5.79 | C11: 0.03 | D11: 0.085 | E11: =B11*(1+C11)/(D11-C11) -> 108.43091 | F11: =E11*1000/$B$7 -> 699.55425
A12: Aladdin Technology (prob-weighted) | B12: 0.575 | C12: 0.08 | D12: 0.1125 | E12: =B12*(1+C12)/(D12-C12) -> 19.107692 | F12: =E12*1000/$B$7 -> 123.27543
A13: GIP Infrastructure | B13: 0.248 | C13: 0.05 | D13: 0.1 | E13: =B13*(1+C13)/(D13-C13) -> 5.208 | F13: =E13*1000/$B$7 -> 33.6
A14: HPS Private Credit | B14: 0.288 | C14: 0.04 | D14: 0.1 | E14: =B14*(1+C14)/(D14-C14) -> 4.992 | F14: =E14*1000/$B$7 -> 32.206452
A15: Gross segment sum | E15: =SUM(E11:E14) -> 137.7386 | F15: =E15*1000/$B$7 -> 888.63614
A16: Less: net debt | E16: -3.5 | F16: =E16*1000/$B$7 -> -22.580645
A17: Less: co-invest capital drag | E17: -3.1 | F17: =E17*1000/$B$7 -> -20
A18: Plus: platform / operating-leverage overlay | E18: 17.5 | F18: =E18*1000/$B$7 -> 112.90323
A19: NET SOTP — Platform Compounder lens | E19: =E15+E16+E17+E18 -> 148.6386 | F19: =E19*1000/$B$7 -> 958.95872
A21: BLENDED COST OF EQUITY CHECK (op-income weighted)
A22: Weights: iShares / Aladdin / HPS / GIP | B22: 0.75 | C22: 0.12 | D22: 0.07 | E22: 0.05
A23: Blended Ke (should ≈ 8.92%) | B23: =B22*D11+C22*D12+D22*D14+E22*D13 -> 0.08925

Sheet Sensitivity
A1: Sensitivity — fair value per share
A2: Rows: iShares cost of equity · Columns: Aladdin probability-weighted FCFE ($B)
A4: iShares Ke \ Aladdin FCFE | B4: 0.5 | C4: 0.575 | D4: 0.65
A5: 0.09 | B5: =(SOTP!$B$11*(1+SOTP!$C$11)/($A5-SOTP!$C$11)+B$4*(1+SOTP!$C$12)/(SOTP!$D$12-SOTP!$C$12)+SOTP!$E$13+SOTP!$E$14+SOTP!$E$16+SOTP!$E$17+SOTP!$E$18)*1000/SOTP!$B$7 -> 884.58313 | C5: =(SOTP!$B$11*(1+SOTP!$C$11)/($A5-SOTP!$C$11)+C$4*(1+SOTP!$C$12)/(SOTP!$D$12-SOTP!$C$12)+SOTP!$E$13+SOTP!$E$14+SOTP!$E$16+SOTP!$E$17+SOTP!$E$18)*1000/SOTP!$B$7 -> 900.66253 | D5: =(SOTP!$B$11*(1+SOTP!$C$11)/($A5-SOTP!$C$11)+D$4*(1+SOTP!$C$12)/(SOTP!$D$12-SOTP!$C$12)+SOTP!$E$13+SOTP!$E$14+SOTP!$E$16+SOTP!$E$17+SOTP!$E$18)*1000/SOTP!$B$7 -> 916.74194
A6: 0.0875 | B6: =(SOTP!$B$11*(1+SOTP!$C$11)/($A6-SOTP!$C$11)+B$4*(1+SOTP!$C$12)/(SOTP!$D$12-SOTP!$C$12)+SOTP!$E$13+SOTP!$E$14+SOTP!$E$16+SOTP!$E$17+SOTP!$E$18)*1000/SOTP!$B$7 -> 912.46391 | C6: =(SOTP!$B$11*(1+SOTP!$C$11)/($A6-SOTP!$C$11)+C$4*(1+SOTP!$C$12)/(SOTP!$D$12-SOTP!$C$12)+SOTP!$E$13+SOTP!$E$14+SOTP!$E$16+SOTP!$E$17+SOTP!$E$18)*1000/SOTP!$B$7 -> 928.54332 | D6: =(SOTP!$B$11*(1+SOTP!$C$11)/($A6-SOTP!$C$11)+D$4*(1+SOTP!$C$12)/(SOTP!$D$12-SOTP!$C$12)+SOTP!$E$13+SOTP!$E$14+SOTP!$E$16+SOTP!$E$17+SOTP!$E$18)*1000/SOTP!$B$7 -> 944.62272
A7: 0.085 | B7: =(SOTP!$B$11*(1+SOTP!$C$11)/($A7-SOTP!$C$11)+B$4*(1+SOTP!$C$12)/(SOTP!$D$12-SOTP!$C$12)+SOTP!$E$13+SOTP!$E$14+SOTP!$E$16+SOTP!$E$17+SOTP!$E$18)*1000/SOTP!$B$7 -> 942.87931 | C7: =(SOTP!$B$11*(1+SOTP!$C$11)/($A7-SOTP!$C$11)+C$4*(1+SOTP!$C$12)/(SOTP!$D$12-SOTP!$C$12)+SOTP!$E$13+SOTP!$E$14+SOTP!$E$16+SOTP!$E$17+SOTP!$E$18)*1000/SOTP!$B$7 -> 958.95872 | D7: =(SOTP!$B$11*(1+SOTP!$C$11)/($A7-SOTP!$C$11)+D$4*(1+SOTP!$C$12)/(SOTP!$D$12-SOTP!$C$12)+SOTP!$E$13+SOTP!$E$14+SOTP!$E$16+SOTP!$E$17+SOTP!$E$18)*1000/SOTP!$B$7 -> 975.03812
A8: 0.0825 | B8: =(SOTP!$B$11*(1+SOTP!$C$11)/($A8-SOTP!$C$11)+B$4*(1+SOTP!$C$12)/(SOTP!$D$12-SOTP!$C$12)+SOTP!$E$13+SOTP!$E$14+SOTP!$E$16+SOTP!$E$17+SOTP!$E$18)*1000/SOTP!$B$7 -> 976.19142 | C8: =(SOTP!$B$11*(1+SOTP!$C$11)/($A8-SOTP!$C$11)+C$4*(1+SOTP!$C$12)/(SOTP!$D$12-SOTP!$C$12)+SOTP!$E$13+SOTP!$E$14+SOTP!$E$16+SOTP!$E$17+SOTP!$E$18)*1000/SOTP!$B$7 -> 992.27083 | D8: =(SOTP!$B$11*(1+SOTP!$C$11)/($A8-SOTP!$C$11)+D$4*(1+SOTP!$C$12)/(SOTP!$D$12-SOTP!$C$12)+SOTP!$E$13+SOTP!$E$14+SOTP!$E$16+SOTP!$E$17+SOTP!$E$18)*1000/SOTP!$B$7 -> 1008.3502
A9: 0.08 | B9: =(SOTP!$B$11*(1+SOTP!$C$11)/($A9-SOTP!$C$11)+B$4*(1+SOTP!$C$12)/(SOTP!$D$12-SOTP!$C$12)+SOTP!$E$13+SOTP!$E$14+SOTP!$E$16+SOTP!$E$17+SOTP!$E$18)*1000/SOTP!$B$7 -> 1012.8347 | C9: =(SOTP!$B$11*(1+SOTP!$C$11)/($A9-SOTP!$C$11)+C$4*(1+SOTP!$C$12)/(SOTP!$D$12-SOTP!$C$12)+SOTP!$E$13+SOTP!$E$14+SOTP!$E$16+SOTP!$E$17+SOTP!$E$18)*1000/SOTP!$B$7 -> 1028.9141 | D9: =(SOTP!$B$11*(1+SOTP!$C$11)/($A9-SOTP!$C$11)+D$4*(1+SOTP!$C$12)/(SOTP!$D$12-SOTP!$C$12)+SOTP!$E$13+SOTP!$E$14+SOTP!$E$16+SOTP!$E$17+SOTP!$E$18)*1000/SOTP!$B$7 -> 1044.9935
A11: Central case (Ke 8.50%, Aladdin $0.575B) ties to the $959 base.
A12: Defensible range across the grid: roughly $885 – $1,045.

Sheet Two Lenses
A1: One Asset, Two Lenses — the bridge
A3: Current market price ($/sh) | B3: 1050
A5: LENS | B5: Fair value $/sh | C5: vs. current price
A6: Platform Compounder (base case) | B6: =SOTP!F19 -> 958.95872 | C6: =B6/$B$3-1 -> -0.086705982
A7: Rate-Sensitive Asset Manager | B7: 825 | C7: =B7/$B$3-1 -> -0.21428571
A8: Market-implied (the third lens) | B8: =B3 -> 1050 | C8: =B8/$B$3-1 -> 0
A10: SCENARIO | B10: $/sh | C10: upside / (downside)
A11: Bull — $35B 2030 path; Aladdin re-rates | B11: 1147 | C11: =B11/$B$3-1 -> 0.092380952
A12: Base — platform lens | B12: =SOTP!F19 -> 958.95872 | C12: =B12/$B$3-1 -> -0.086705982
A13: Bear — rate-sensitive lens dominates | B13: 825 | C13: =B13/$B$3-1 -> -0.21428571
A15: Recommendation: HOLD. Skew unfavorable above $1,000; accumulate in the high-$900s where the lenses converge.

Sheet Assumptions
A1: Key Assumptions & Sources
A3: Input | B3: Value | C3: Source / note (refreshed items flagged)
A4: Share price | B4: ~$1,050 | C4: NYSE BLK, mid-June 2026 [REFRESHED from $1,085]
A5: Market cap | B5: ~$163B | C5: Price × 155M shares [REFRESHED]
A6: AUM | B6: $13.9T | C6: BLK Q1 2026 8-K, 3/31/26 [REFRESHED from $14.0T]
A7: LTM net inflows | B7: $744B | C7: BLK Q1 2026 release [REFRESHED from $698B FY25]
A8: Organic base-fee growth | B8: 10% LTM / 8% Q1 | C8: BLK Q1 2026 — best Q1 in 5 years [NEW]
A9: Q1 2026 adjusted EPS | B9: $12.53 | C9: Beat $11.48 consensus [NEW]
A10: Technology services ACV growth | B10: +14% | C10: BLK Q1 2026 [REFRESHED, slight decel]
A11: Risk-free rate (Rf) | B11: 4.45% | C11: Fed H.15 10Y, June 2026 [REFRESHED from 4.30%]
A12: Fed posture | B12: Hawkish | C12: New chair Warsh; ~half of FOMC sees a 2026 hike [NEW]
A13: Private credit | B13: Redemptions gated | C13: ~$1.2B gated Mar 2026; renewed pressure Jun 2026 [NEW — key risk]
A14: Blended ERP | B14: 5.40% | C14: Damodaran Apr 2026, geographic-weighted
... A21: BLK EV/EBIT | B21: ~16x | C21: Hybrid: premium to peers, discount to sector
A23: This workbook is an academic exercise and does not constitute investment advice.
